kitconcept.glossary-1.1.0-py3.7-nspkg.pth
kitconcept/glossary/__init__.py
kitconcept/glossary/config.py
kitconcept/glossary/configure.zcml
kitconcept/glossary/content.py
kitconcept/glossary/controlpanel.py
kitconcept/glossary/indexers.py
kitconcept/glossary/interfaces.py
kitconcept/glossary/logger.py
kitconcept/glossary/profiles.zcml
kitconcept/glossary/setuphandlers.py
kitconcept/glossary/testing.py
kitconcept/glossary/upgrades.py
kitconcept/glossary/upgrades.zcml
kitconcept/glossary/utils.py
kitconcept/glossary/vocabulary.py
kitconcept/glossary/vocabulary.zcml
kitconcept/glossary/Extensions/Install.py
kitconcept/glossary/Extensions/__init__.py
kitconcept/glossary/api/__init__.py
kitconcept/glossary/api/configure.zcml
kitconcept/glossary/api/serializers/__init__.py
kitconcept/glossary/api/serializers/configure.zcml
kitconcept/glossary/api/services/__init__.py
kitconcept/glossary/api/services/configure.zcml
kitconcept/glossary/api/services/glossary/__init__.py
kitconcept/glossary/api/services/glossary/configure.zcml
kitconcept/glossary/api/services/glossary/get.py
kitconcept/glossary/browser/__init__.py
kitconcept/glossary/browser/configure.zcml
kitconcept/glossary/browser/views.py
kitconcept/glossary/browser/static/README.rst
kitconcept/glossary/browser/static/glossary-5968e5a.css
kitconcept/glossary/browser/static/glossary-5968e5a.js
kitconcept/glossary/browser/static/resources.pt
kitconcept/glossary/browser/static/img/glossary-icon.png
kitconcept/glossary/browser/static/img/ploneglossarydefinition_icon.png
kitconcept/glossary/browser/static/img/term-icon.png
kitconcept/glossary/browser/templates/glossary.pt
kitconcept/glossary/browser/templates/term.pt
kitconcept/glossary/locales/collective.glossary.pot
kitconcept/glossary/locales/kitconcept.glossary.pot
kitconcept/glossary/locales/de/LC_MESSAGES/kitconcept.glossary.mo
kitconcept/glossary/locales/de/LC_MESSAGES/kitconcept.glossary.po
kitconcept/glossary/profiles/default/browserlayer.xml
kitconcept.glossary-1.1.0.dist-info/METADATA
kitconcept.glossary-1.1.0.dist-info/WHEEL
kitconcept.glossary-1.1.0.dist-info/entry_points.txt
kitconcept.glossary-1.1.0.dist-info/namespace_packages.txt
kitconcept.glossary-1.1.0.dist-info/top_level.txt
kitconcept.glossary-1.1.0.dist-info/RECORD
