Metadata-Version: 2.1
Name: kitconcept.glossary
Version: 1.1.0
Summary: Plone add-on product to define a glossary.
Home-page: https://github.com/kitconcept/kitconcept.glossary
Author: kitconcept GmbH
Author-email: info@kitconcept.com
License: GPL version 2
Keywords: plone glossary
Platform: UNKNOWN
Classifier: Development Status :: 4 - Beta
Classifier: Environment :: Web Environment
Classifier: Framework :: Plone
Classifier: Framework :: Plone :: 4.3
Classifier: Framework :: Plone :: 5.1
Classifier: Framework :: Plone :: 5.2
Classifier: Intended Audience :: Education
Classifier: Intended Audience :: End Users/Desktop
Classifier: License :: OSI Approved :: GNU General Public License v2 (GPLv2)
Classifier: Operating System :: OS Independent
Classifier: Programming Language :: Python
Classifier: Programming Language :: Python :: 2.7
Classifier: Programming Language :: Python :: 3.7
Classifier: Programming Language :: Python :: 3.8
Classifier: Topic :: Software Development :: Libraries :: Python Modules
Requires-Dist: plone.api
Requires-Dist: plone.app.dexterity
Requires-Dist: plone.app.registry
Requires-Dist: plone.dexterity
Requires-Dist: plone.namedfile
Requires-Dist: plone.restapi
Requires-Dist: Products.CMFPlone (>=4.3)
Requires-Dist: Products.GenericSetup
Requires-Dist: setuptools
Requires-Dist: zope.globalrequest
Requires-Dist: zope.i18nmessageid
Requires-Dist: zope.interface
Requires-Dist: zope.schema
Provides-Extra: test
Requires-Dist: AccessControl ; extra == 'test'
Requires-Dist: plone.app.robotframework ; extra == 'test'
Requires-Dist: plone.app.testing[robot] ; extra == 'test'
Requires-Dist: plone.browserlayer ; extra == 'test'
Requires-Dist: plone.registry ; extra == 'test'
Requires-Dist: plone.testing ; extra == 'test'
Requires-Dist: robotsuite ; extra == 'test'
Requires-Dist: zope.component ; extra == 'test'
